distan2_matr/__init__.py
distan2_matr/tran.cpython-311-darwin.so
distan2_matr-0.1.2.dist-info/LICENCE.txt
distan2_matr-0.1.2.dist-info/METADATA
distan2_matr-0.1.2.dist-info/WHEEL
distan2_matr-0.1.2.dist-info/top_level.txt
distan2_matr-0.1.2.dist-info/RECORD
