Metadata-Version: 2.1
Name: distan2-matr
Version: 0.1.2
Summary: A package for processing FASTA files
Author: Geroge
Author-email: 
Classifier: Programming Language :: Python :: 3
Classifier: Programming Language :: Python :: 3.7
Classifier: Programming Language :: Python :: 3.8
Classifier: Programming Language :: Python :: 3.9
License-File: LICENCE.txt
Requires-Dist: pandas
